{
 "rankedTeams": [
  {
   "name": "Joblife",
   "country": "France",
   "ratio": "7-2"
  },
  {
   "name": "Gentle Mates",
   "country": "France",
   "ratio": "6-3"
  },
  {
   "name": "VALIANT",
   "country": "France",
   "ratio": "6-3"
  },
  {
   "name": "Mandatory",
   "country": "France",
   "ratio": "6-3"
  },
  {
   "name": "Solary",
   "country": "France",
   "ratio": "5-4"
  },
  {
   "name": "WYLDE",
   "country": "Netherlands",
   "ratio": "5-4"
  },
  {
   "name": "Zerance",
   "country": "France",
   "ratio": "4-5"
  },
  {
   "name": "3DMAX",
   "country": "France",
   "ratio": "2-7"
  },
  {
   "name": "BLX UTD",
   "country": "Europe",
   "ratio": "2-7"
  },
  {
   "name": "Akroma",
   "country": "France",
   "ratio": "2-7"
  }
 ],
 "updateTime": "30/04/23 - 08h30"
}